pygame_gui/__init__.py
pygame_gui/_constants.py
pygame_gui/py.typed
pygame_gui/ui_manager.py
pygame_gui/__pyinstaller/__init__.py
pygame_gui/__pyinstaller/hook-pygame_gui.py
pygame_gui/core/__init__.py
pygame_gui/core/colour_gradient.py
pygame_gui/core/colour_parser.py
pygame_gui/core/gui_font_freetype.py
pygame_gui/core/gui_font_pygame.py
pygame_gui/core/gui_type_hints.py
pygame_gui/core/layered_gui_group.py
pygame_gui/core/object_id.py
pygame_gui/core/resource_loaders.py
pygame_gui/core/surface_cache.py
pygame_gui/core/ui_appearance_theme.py
pygame_gui/core/ui_container.py
pygame_gui/core/ui_element.py
pygame_gui/core/ui_font_dictionary.py
pygame_gui/core/ui_shadow.py
pygame_gui/core/ui_window_stack.py
pygame_gui/core/utility.py
pygame_gui/core/drawable_shapes/__init__.py
pygame_gui/core/drawable_shapes/drawable_shape.py
pygame_gui/core/drawable_shapes/ellipse_drawable_shape.py
pygame_gui/core/drawable_shapes/rect_drawable_shape.py
pygame_gui/core/drawable_shapes/rounded_rect_drawable_shape.py
pygame_gui/core/interfaces/__init__.py
pygame_gui/core/interfaces/appearance_theme_interface.py
pygame_gui/core/interfaces/colour_gradient_interface.py
pygame_gui/core/interfaces/container_interface.py
pygame_gui/core/interfaces/element_interface.py
pygame_gui/core/interfaces/font_dictionary_interface.py
pygame_gui/core/interfaces/gui_font_interface.py
pygame_gui/core/interfaces/gui_sprite_interface.py
pygame_gui/core/interfaces/manager_interface.py
pygame_gui/core/interfaces/text_owner_interface.py
pygame_gui/core/interfaces/tool_tip_interface.py
pygame_gui/core/interfaces/window_interface.py
pygame_gui/core/interfaces/window_stack_interface.py
pygame_gui/core/text/__init__.py
pygame_gui/core/text/horiz_rule_layout_rect.py
pygame_gui/core/text/html_parser.py
pygame_gui/core/text/hyperlink_text_chunk.py
pygame_gui/core/text/image_layout_rect.py
pygame_gui/core/text/line_break_layout_rect.py
pygame_gui/core/text/simple_test_layout_rect.py
pygame_gui-0.6.11.dist-info/LICENSE.txt
pygame_gui-0.6.11.dist-info/METADATA
pygame_gui-0.6.11.dist-info/WHEEL
pygame_gui-0.6.11.dist-info/entry_points.txt
pygame_gui-0.6.11.dist-info/top_level.txt
pygame_gui-0.6.11.dist-info/RECORD
